msg91/__init__.py
msg91/client.py
msg91/exceptions.py
msg91/http_client.py
msg91/py.typed
msg91/version.py
msg91/resources/__init__.py
msg91/resources/base.py
msg91/resources/otp.py
msg91/resources/sms.py
msg91/resources/template.py
msg91_py-0.2.1.dist-info/METADATA
msg91_py-0.2.1.dist-info/WHEEL
msg91_py-0.2.1.dist-info/licenses/LICENSE
msg91_py-0.2.1.dist-info/RECORD
