Metadata-Version: 2.4
Name: msg91-py
Version: 0.2.1
Summary: A Python client library for the MSG91 SMS API
Project-URL: Homepage, https://github.com/karambir/msg91-py
Project-URL: Documentation, https://github.com/karambir/msg91-py
Project-URL: Issues, https://github.com/karambir/msg91-py/issues
Author-email: Karambir Singh Nain <akarambir@gmail.com>
License-File: LICENSE
Classifier: Development Status :: 4 - Beta
Classifier: Intended Audience :: Developers
Classifier: License :: OSI Approved :: MIT License
Classifier: Programming Language :: Python :: 3
Classifier: Programming Language :: Python :: 3.9
Classifier: Programming Language :: Python :: 3.10
Classifier: Programming Language :: Python :: 3.11
Classifier: Programming Language :: Python :: 3.12
Classifier: Programming Language :: Python :: 3.13
Classifier: Programming Language :: Python :: 3.14
Classifier: Topic :: Communications :: Telephony
Requires-Python: >=3.9
Requires-Dist: httpx>=0.24.0
Requires-Dist: typing-extensions>=4.5.0
